pyflatpak/__init__.py
pyflatpak-0.0.1.dist-info/METADATA
pyflatpak-0.0.1.dist-info/WHEEL
pyflatpak-0.0.1.dist-info/top_level.txt
pyflatpak-0.0.1.dist-info/RECORD
